odoo/addons/l10n_it_fatturapa_in_rc/README.rst
odoo/addons/l10n_it_fatturapa_in_rc/__init__.py
odoo/addons/l10n_it_fatturapa_in_rc/__manifest__.py
odoo/addons/l10n_it_fatturapa_in_rc/i18n/l10n_it_fatturapa_in_rc.pot
odoo/addons/l10n_it_fatturapa_in_rc/models/__init__.py
odoo/addons/l10n_it_fatturapa_in_rc/models/account_invoice.py
odoo/addons/l10n_it_fatturapa_in_rc/models/account_rc_type.py
odoo/addons/l10n_it_fatturapa_in_rc/models/attachment.py
odoo/addons/l10n_it_fatturapa_in_rc/readme/CONFIGURE.rst
odoo/addons/l10n_it_fatturapa_in_rc/readme/CONTRIBUTORS.rst
odoo/addons/l10n_it_fatturapa_in_rc/readme/DESCRIPTION.rst
odoo/addons/l10n_it_fatturapa_in_rc/static/description/icon.png
odoo/addons/l10n_it_fatturapa_in_rc/static/description/index.html
odoo/addons/l10n_it_fatturapa_in_rc/tests/__init__.py
odoo/addons/l10n_it_fatturapa_in_rc/tests/test_fatturapa_in_rc.py
odoo/addons/l10n_it_fatturapa_in_rc/tests/data/IT01234567890_FPR04.xml
odoo/addons/l10n_it_fatturapa_in_rc/views/rc_type_view.xml
odoo/addons/l10n_it_fatturapa_in_rc/wizard/__init__.py
odoo/addons/l10n_it_fatturapa_in_rc/wizard/wizard_import_fatturapa.py
odoo12_addon_l10n_it_fatturapa_in_rc-12.0.1.2.0.dist-info/METADATA
odoo12_addon_l10n_it_fatturapa_in_rc-12.0.1.2.0.dist-info/WHEEL
odoo12_addon_l10n_it_fatturapa_in_rc-12.0.1.2.0.dist-info/top_level.txt
odoo12_addon_l10n_it_fatturapa_in_rc-12.0.1.2.0.dist-info/RECORD
