Metadata-Version: 2.1
Name: odoo12-addon-l10n-it-fatturapa-in-rc
Version: 12.0.1.2.0
Summary: Modulo ponte tra e-fattura in acquisto e inversione contabile
Home-page: https://github.com/OCA/l10n-italy/tree/10.0/l10n_it_fatturapa_in_rc
Author: Efatto.it di Sergio Corato, Odoo Community Association (OCA)
Author-email: support@odoo-community.org
License: AGPL-3
Platform: UNKNOWN
Classifier: Programming Language :: Python
Classifier: Framework :: Odoo
Classifier: Framework :: Odoo :: 12.0
Classifier: License :: OSI Approved :: GNU Affero General Public License v3
Classifier: Development Status :: 4 - Beta
Requires-Python: >=3.5
Requires-Dist: odoo12-addon-l10n-it-account-tax-kind
Requires-Dist: odoo12-addon-l10n-it-fatturapa-in
Requires-Dist: odoo12-addon-l10n-it-reverse-charge
Requires-Dist: odoo (<12.1dev,>=12.0a)
